code2img/__init__.py
code2img/__main__.py
code2img/api.py
code2img/base.py
code2img/constants.py
code2img/creator.py
code2img/utils.py
code2img-0.0.3.dist-info/LICENSE
code2img-0.0.3.dist-info/METADATA
code2img-0.0.3.dist-info/WHEEL
code2img-0.0.3.dist-info/entry_points.txt
code2img-0.0.3.dist-info/top_level.txt
code2img-0.0.3.dist-info/RECORD
