Metadata-Version: 2.1
Name: code2img
Version: 0.0.3
Summary: Generate an image from source code (local or repository)
Home-page: https://github.com/leugimkm/code2img
Author: leugimkm
Author-email: leugimkm@systrien.com
License: MIT
Project-URL: Documentation, https://leugimkm.github.io/code2img/
Project-URL: Tracker, https://github.com/leugimkm/code2img/issues
Project-URL: Source, https://github.com/leugimkm/code2img
Platform: UNKNOWN
Classifier: Environment :: Console
Classifier: Intended Audience :: Developers
Classifier: License :: OSI Approved :: MIT License
Classifier: Programming Language :: Python :: 3.7
Classifier: Programming Language :: Python :: 3.8
Classifier: Programming Language :: Python :: 3.9
Classifier: Programming Language :: Python :: 3.10
Classifier: Operating System :: OS Independent
Classifier: Programming Language :: Python :: Implementation :: CPython
Classifier: Programming Language :: Python :: Implementation :: PyPy
Classifier: Topic :: Software Development :: Libraries :: Python Modules
Requires-Python: >=3.7
License-File: LICENSE
